{
    "https://id.reuna.cl/id/saml2/idp/metadata.php": {
        "en": "ID REUNA",
        "es": "ID REUNA"
    },
    "https://idp.beic.cl/idp/shibboleth": {
        "en": "BEIC - ANID",
        "es": "BEIC - ANID"
    },
    "https://idp.utalca.cl/simplesaml/saml2/idp/metadata.php": {
        "en": "Universidad de Talca",
        "es": "Universidad de Talca"
    },
    "https://idp2.reuna.cl/saml2/idp/metadata.php": {
        "en": "Funcionarios REUNA",
        "es": "Funcionarios REUNA"
    },
    "https://idp3.redclara.net/idp/shibboleth": {
        "en": "RedCLARA - Cooperacion Latino Americana de Redes Avanzadas",
        "es": "RedCLARA - Cooperacion Latino Americana de Redes Avanzadas"
    },
    "https://proxy.redclara.net/idp": {
        "en": "RedCLARA Proxy IdP",
        "es": "RedCLARA Proxy IdP"
    },
    "https://sso.uc.cl/cas/idp": {
        "en": "Pontificia Universidad Católica de Chile",
        "es": "Pontificia Universidad Católica de Chile"
    }
}