{
    "https://aai.goscloud.net/saml/idp": {
        "en": "GOSC AAI",
        "zh": "GOSC AAI"
    },
    "https://chinasrcyun.shao.ac.cn/saml/idp": {
        "en": "SKA CN-SRC AAI",
        "zh": "SKA CN-SRC AAI"
    },
    "https://idp.baafs.net.cn/idp/shibboleth": {
        "en": "Beijing Academy of Agriculture and Forestry Sciences",
        "zh": "北京市农林科学院"
    },
    "https://idp.hnas.ac.cn/idp/shibboleth": {
        "en": "Henan Academy of Sciences",
        "zh": "河南省科学院"
    },
    "https://idp.jxas.ac.cn/idp/shibboleth": {
        "en": "JiangXi Academy of Sciences",
        "zh": "江西省科学院"
    },
    "https://idp.las.ac.cn/idp/shibboleth": {
        "en": "National Science Library, Chinese Academy of Sciences",
        "zh": "中国科学院文献情报中心"
    },
    "https://idp.redclara.net/saml2/idp/metadata.php": {
        "en": "RedCLARA - IdP",
        "es": "RedCLARA - IdP"
    },
    "https://idp.scholarin.cn/idp/shibboleth": {
        "en": "Scholarin ID",
        "zh": "慧科研通行证"
    },
    "https://idp.stlib.cn/idp/shibboleth": {
        "en": "Guangdong Science and Technology Library",
        "zh": "广东省科技图书馆"
    },
    "https://idplaconga.redclara.net/simplesaml/saml2/idp/metadata.php": {
        "en": "https://idplaconga.redclara.net/simplesaml/saml2/idp/metadata.php"
    },
    "https://login.imicams.ac.cn/idp/shibboleth": {
        "en": "PUMC ID",
        "zh": "协和统一身份认证"
    },
    "https://passport.escience.cn/idp/shibboleth": {
        "en": "CSTCloud ID",
        "zh": "中国科技云通行证(CSTCloud ID)"
    }
}